ou_logger/__init__.py
ou_logger/logger.py
ou_logger-0.0.2.dist-info/LICENSE
ou_logger-0.0.2.dist-info/METADATA
ou_logger-0.0.2.dist-info/WHEEL
ou_logger-0.0.2.dist-info/top_level.txt
ou_logger-0.0.2.dist-info/RECORD
