Metadata-Version: 2.1
Name: ou_logger
Version: 0.0.2
Summary: A simple logger package for Jupyter Notebooks
Author-email: Tony Hirst <tony.hirst@gmail.com>
License: MIT
License-File: LICENSE
